ai_pipeline_core/__init__.py
ai_pipeline_core/exceptions.py
ai_pipeline_core/pipeline.py
ai_pipeline_core/prefect.py
ai_pipeline_core/progress.py
ai_pipeline_core/prompt_manager.py
ai_pipeline_core/py.typed
ai_pipeline_core/settings.py
ai_pipeline_core/tracing.py
ai_pipeline_core/debug/__init__.py
ai_pipeline_core/debug/config.py
ai_pipeline_core/debug/content.py
ai_pipeline_core/debug/processor.py
ai_pipeline_core/debug/summary.py
ai_pipeline_core/debug/writer.py
ai_pipeline_core/deployment/__init__.py
ai_pipeline_core/deployment/base.py
ai_pipeline_core/deployment/contract.py
ai_pipeline_core/deployment/helpers.py
ai_pipeline_core/documents/__init__.py
ai_pipeline_core/documents/document.py
ai_pipeline_core/documents/document_list.py
ai_pipeline_core/documents/flow_document.py
ai_pipeline_core/documents/mime_type.py
ai_pipeline_core/documents/task_document.py
ai_pipeline_core/documents/temporary_document.py
ai_pipeline_core/documents/utils.py
ai_pipeline_core/flow/__init__.py
ai_pipeline_core/flow/config.py
ai_pipeline_core/flow/options.py
ai_pipeline_core/images/__init__.py
ai_pipeline_core/images/_processing.py
ai_pipeline_core/llm/__init__.py
ai_pipeline_core/llm/ai_messages.py
ai_pipeline_core/llm/client.py
ai_pipeline_core/llm/model_options.py
ai_pipeline_core/llm/model_response.py
ai_pipeline_core/llm/model_types.py
ai_pipeline_core/logging/__init__.py
ai_pipeline_core/logging/logging.yml
ai_pipeline_core/logging/logging_config.py
ai_pipeline_core/logging/logging_mixin.py
ai_pipeline_core/prompt_builder/__init__.py
ai_pipeline_core/prompt_builder/documents_prompt.jinja2
ai_pipeline_core/prompt_builder/global_cache.py
ai_pipeline_core/prompt_builder/new_core_documents_prompt.jinja2
ai_pipeline_core/prompt_builder/prompt_builder.py
ai_pipeline_core/prompt_builder/system_prompt.jinja2
ai_pipeline_core/storage/__init__.py
ai_pipeline_core/storage/storage.py
ai_pipeline_core/utils/__init__.py
ai_pipeline_core/utils/deploy.py
ai_pipeline_core-0.3.4.dist-info/METADATA
ai_pipeline_core-0.3.4.dist-info/WHEEL
ai_pipeline_core-0.3.4.dist-info/licenses/LICENSE
ai_pipeline_core-0.3.4.dist-info/RECORD
