Metadata-Version: 2.4
Name: ai-pipeline-core
Version: 0.3.4
Summary: Core utilities for AI-powered processing pipelines using prefect
Project-URL: Homepage, https://github.com/bbarwik/ai-pipeline-core
Project-URL: Repository, https://github.com/bbarwik/ai-pipeline-core
Project-URL: Issues, https://github.com/bbarwik/ai-pipeline-core/issues
Author-email: bbarwik <bbarwik@gmail.com>
License: MIT
License-File: LICENSE
Classifier: Development Status :: 4 - Beta
Classifier: Intended Audience :: Developers
Classifier: License :: OSI Approved :: MIT License
Classifier: Programming Language :: Python :: 3
Classifier: Programming Language :: Python :: 3.12
Classifier: Programming Language :: Python :: 3.13
Classifier: Topic :: Scientific/Engineering :: Artificial Intelligence
Classifier: Topic :: Software Development :: Libraries :: Python Modules
Classifier: Typing :: Typed
Requires-Python: >=3.12
Requires-Dist: httpx>=0.28.1
Requires-Dist: jinja2>=3.1.6
Requires-Dist: lmnr>=0.7.18
Requires-Dist: openai>=1.109.1
Requires-Dist: pillow>=10.0.0
Requires-Dist: prefect-gcp[cloud-storage]>=0.6.10
Requires-Dist: prefect>=3.4.21
Requires-Dist: pydantic-settings>=2.10.1
Requires-Dist: pydantic>=2.11.9
Requires-Dist: python-magic>=0.4.27
Requires-Dist: ruamel-yaml>=0.18.14
Requires-Dist: tiktoken>=0.12.0
Provides-Extra: dev
Requires-Dist: basedpyright>=1.31.2; extra == 'dev'
Requires-Dist: bump2version>=1.0.1; extra == 'dev'
Requires-Dist: interrogate>=1.5.0; extra == 'dev'
Requires-Dist: pre-commit>=4.3.0; extra == 'dev'
Requires-Dist: pydoc-markdown[jinja]>=4.8.0; extra == 'dev'
Requires-Dist: pytest-asyncio>=1.1.0; extra == 'dev'
Requires-Dist: pytest-cov>=5.0.0; extra == 'dev'
Requires-Dist: pytest-mock>=3.14.0; extra == 'dev'
Requires-Dist: pytest-xdist>=3.8.0; extra == 'dev'
Requires-Dist: pytest>=8.4.1; extra == 'dev'
Requires-Dist: ruff>=0.14.1; extra == 'dev'
